d1_csw/__init__.py
d1_csw/nodc_adapter/src/nodc_adapter/__init__.py
d1_csw/tests/__init__.py
dataone.csw-3.5.2.dist-info/METADATA
dataone.csw-3.5.2.dist-info/WHEEL
dataone.csw-3.5.2.dist-info/top_level.txt
dataone.csw-3.5.2.dist-info/RECORD
